[
  {
    "id": "s9_2_1",
    "level": "calculus",
    "title": "다항식 미분",
    "variable": [],
    "answer": {
      "expression": "d/dx x^3=3*x^2",
      "display": "d/dx x^3=3*x^2",
      "cells": [
        {
          "type": "block",
          "blockType": "d/dx",
          "fields": {}
        },
        {
          "type": "token",
          "value": "x"
        },
        {
          "type": "token",
          "value": "^"
        },
        {
          "type": "token",
          "value": "3"
        },
        {
          "type": "token",
          "value": "="
        },
        {
          "type": "token",
          "value": "3"
        },
        {
          "type": "token",
          "value": "*"
        },
        {
          "type": "token",
          "value": "x"
        },
        {
          "type": "token",
          "value": "^"
        },
        {
          "type": "token",
          "value": "2"
        }
      ],
      "length": 10
    },
    "difficulty": "medium",
    "category": "function",
    "rules": {},
    "shownTokens": [
      "0",
      "1",
      "2",
      "3",
      "4",
      "5",
      "6",
      "7",
      "8",
      "9",
      "=",
      "*",
      "^",
      "x"
    ],
    "shownBlocks": [
      "d/dx"
    ],
    "explanation": "x^3를 x에 대해 미분하면 3*x^2가 된다.",
    "puzzle": "d/dx x^3=3*x^2"
  },
  {
    "id": "s9_2_2",
    "level": "calculus",
    "title": "다항식 미분",
    "variable": [],
    "answer": {
      "expression": "d/dx x^3=3*x^2",
      "display": "d/dx x^3=3*x^2",
      "cells": [
        {
          "type": "block",
          "blockType": "d/dx",
          "fields": {}
        },
        {
          "type": "token",
          "value": "x"
        },
        {
          "type": "token",
          "value": "^"
        },
        {
          "type": "token",
          "value": "3"
        },
        {
          "type": "token",
          "value": "="
        },
        {
          "type": "token",
          "value": "3"
        },
        {
          "type": "token",
          "value": "*"
        },
        {
          "type": "token",
          "value": "x"
        },
        {
          "type": "token",
          "value": "^"
        },
        {
          "type": "token",
          "value": "2"
        }
      ],
      "length": 10
    },
    "difficulty": "medium",
    "category": "function",
    "rules": {},
    "shownTokens": [
      "0",
      "1",
      "2",
      "3",
      "4",
      "5",
      "6",
      "7",
      "8",
      "9",
      "=",
      "*",
      "^",
      "x"
    ],
    "shownBlocks": [
      "d/dx"
    ],
    "explanation": "x^3를 x에 대해 미분하면 3*x^2가 된다.",
    "puzzle": "d/dx x^3=3*x^2"
  },
  {
    "id": "s9_2_3",
    "level": "calculus",
    "title": "다항식 미분",
    "variable": [],
    "answer": {
      "expression": "d/dx x^3=3*x^2",
      "display": "d/dx x^3=3*x^2",
      "cells": [
        {
          "type": "block",
          "blockType": "d/dx",
          "fields": {}
        },
        {
          "type": "token",
          "value": "x"
        },
        {
          "type": "token",
          "value": "^"
        },
        {
          "type": "token",
          "value": "3"
        },
        {
          "type": "token",
          "value": "="
        },
        {
          "type": "token",
          "value": "3"
        },
        {
          "type": "token",
          "value": "*"
        },
        {
          "type": "token",
          "value": "x"
        },
        {
          "type": "token",
          "value": "^"
        },
        {
          "type": "token",
          "value": "2"
        }
      ],
      "length": 10
    },
    "difficulty": "medium",
    "category": "function",
    "rules": {},
    "shownTokens": [
      "0",
      "1",
      "2",
      "3",
      "4",
      "5",
      "6",
      "7",
      "8",
      "9",
      "=",
      "*",
      "^",
      "x"
    ],
    "shownBlocks": [
      "d/dx"
    ],
    "explanation": "x^3를 x에 대해 미분하면 3*x^2가 된다.",
    "puzzle": "d/dx x^3=3*x^2"
  },
  {
    "id": "s9_2_4",
    "level": "calculus",
    "title": "다항식 미분",
    "variable": [],
    "answer": {
      "expression": "d/dx x^3=3*x^2",
      "display": "d/dx x^3=3*x^2",
      "cells": [
        {
          "type": "block",
          "blockType": "d/dx",
          "fields": {}
        },
        {
          "type": "token",
          "value": "x"
        },
        {
          "type": "token",
          "value": "^"
        },
        {
          "type": "token",
          "value": "3"
        },
        {
          "type": "token",
          "value": "="
        },
        {
          "type": "token",
          "value": "3"
        },
        {
          "type": "token",
          "value": "*"
        },
        {
          "type": "token",
          "value": "x"
        },
        {
          "type": "token",
          "value": "^"
        },
        {
          "type": "token",
          "value": "2"
        }
      ],
      "length": 10
    },
    "difficulty": "medium",
    "category": "function",
    "rules": {},
    "shownTokens": [
      "0",
      "1",
      "2",
      "3",
      "4",
      "5",
      "6",
      "7",
      "8",
      "9",
      "=",
      "*",
      "^",
      "x"
    ],
    "shownBlocks": [
      "d/dx"
    ],
    "explanation": "x^3를 x에 대해 미분하면 3*x^2가 된다.",
    "puzzle": "d/dx x^3=3*x^2"
  },
  {
    "id": "s9_2_5",
    "level": "calculus",
    "title": "다항식 미분",
    "variable": [],
    "answer": {
      "expression": "d/dx x^3=3*x^2",
      "display": "d/dx x^3=3*x^2",
      "cells": [
        {
          "type": "block",
          "blockType": "d/dx",
          "fields": {}
        },
        {
          "type": "token",
          "value": "x"
        },
        {
          "type": "token",
          "value": "^"
        },
        {
          "type": "token",
          "value": "3"
        },
        {
          "type": "token",
          "value": "="
        },
        {
          "type": "token",
          "value": "3"
        },
        {
          "type": "token",
          "value": "*"
        },
        {
          "type": "token",
          "value": "x"
        },
        {
          "type": "token",
          "value": "^"
        },
        {
          "type": "token",
          "value": "2"
        }
      ],
      "length": 10
    },
    "difficulty": "medium",
    "category": "function",
    "rules": {},
    "shownTokens": [
      "0",
      "1",
      "2",
      "3",
      "4",
      "5",
      "6",
      "7",
      "8",
      "9",
      "=",
      "*",
      "^",
      "x"
    ],
    "shownBlocks": [
      "d/dx"
    ],
    "explanation": "x^3를 x에 대해 미분하면 3*x^2가 된다.",
    "puzzle": "d/dx x^3=3*x^2"
  }
]